ScoreCardModel/__init__.py
ScoreCardModel/discretization.py
ScoreCardModel/score_card.py
ScoreCardModel/weight_of_evidence.py
ScoreCardModel/binning/__init__.py
ScoreCardModel/binning/discretization.py
ScoreCardModel/mixins/__init__.py
ScoreCardModel/mixins/serialize_mixin.py
ScoreCardModel/models/LinearSVC_model.py
ScoreCardModel/models/MLP_model.py
ScoreCardModel/models/NuSVC_model.py
ScoreCardModel/models/SVC_model.py
ScoreCardModel/models/__init__.py
ScoreCardModel/models/logistic_regression_model.py
ScoreCardModel/models/meta.py
ScoreCardModel-1.1.3.data/data/requirements/requirements.txt
ScoreCardModel-1.1.3.data/data/requirements/requirements_dev.txt
ScoreCardModel-1.1.3.data/data/requirements/requirements_test.txt
ScoreCardModel-1.1.3.dist-info/DESCRIPTION.rst
ScoreCardModel-1.1.3.dist-info/METADATA
ScoreCardModel-1.1.3.dist-info/RECORD
ScoreCardModel-1.1.3.dist-info/WHEEL
ScoreCardModel-1.1.3.dist-info/metadata.json
ScoreCardModel-1.1.3.dist-info/top_level.txt
ScoreCardModel-1.1.3.dist-info/zip-safe
