Metadata-Version: 2.0
Name: ScoreCardModel
Version: 1.1.3
Summary: simple tools for score card model
Home-page: https://data-science-tools.github.io/ScoreCardModel/
Author: hsz
Author-email: hsz1273327@gmail.com
License: MIT
Requires-Dist: numpy
Requires-Dist: scipy
Requires-Dist: scikit-learn
Requires-Dist: pandas
Requires-Dist: cython
Requires-Dist: dill
Provides-Extra: dev
Requires-Dist: wheel; extra == 'dev'
Provides-Extra: test
Requires-Dist: coverage; extra == 'test'
